django_template_forms-0.3.1.dist-info/DESCRIPTION.rst
django_template_forms-0.3.1.dist-info/METADATA
django_template_forms-0.3.1.dist-info/RECORD
django_template_forms-0.3.1.dist-info/WHEEL
django_template_forms-0.3.1.dist-info/metadata.json
django_template_forms-0.3.1.dist-info/top_level.txt
template_forms/__init__.py
template_forms/base.py
template_forms/bs3.py
template_forms/bs4.py
template_forms/utils.py
template_forms/templates/template_forms/bs3/fields/block.html
template_forms/templates/template_forms/bs3/fields/block_checkbox.html
template_forms/templates/template_forms/bs3/fields/horizontal.html
template_forms/templates/template_forms/bs3/fields/horizontal_checkbox.html
template_forms/templates/template_forms/bs3/forms/block.html
template_forms/templates/template_forms/bs3/forms/horizontal.html
template_forms/templates/template_forms/bs4/fields/block.html
template_forms/templates/template_forms/bs4/forms/block.html
